llm_council/__init__.py
llm_council/_version.py
llm_council/bias_aggregation.py
llm_council/bias_audit.py
llm_council/bias_persistence.py
llm_council/cache.py
llm_council/cli.py
llm_council/cost_ceiling.py
llm_council/council.py
llm_council/dissent.py
llm_council/evaluation.py
llm_council/frontier_fallback.py
llm_council/gateway_adapter.py
llm_council/graduation.py
llm_council/http_server.py
llm_council/layer_contracts.py
llm_council/mcp_server.py
llm_council/openrouter.py
llm_council/rubric.py
llm_council/safety_gate.py
llm_council/telemetry.py
llm_council/telemetry_client.py
llm_council/tier_contract.py
llm_council/unified_config.py
llm_council/verdict.py
llm_council/voting.py
llm_council/audition/__init__.py
llm_council/audition/selection.py
llm_council/audition/store.py
llm_council/audition/tracker.py
llm_council/audition/types.py
llm_council/audition/voting.py
llm_council/gateway/__init__.py
llm_council/gateway/base.py
llm_council/gateway/circuit_breaker.py
llm_council/gateway/circuit_breaker_registry.py
llm_council/gateway/direct.py
llm_council/gateway/errors.py
llm_council/gateway/ollama.py
llm_council/gateway/openrouter.py
llm_council/gateway/requesty.py
llm_council/gateway/router.py
llm_council/gateway/types.py
llm_council/metadata/__init__.py
llm_council/metadata/cache.py
llm_council/metadata/discovery.py
llm_council/metadata/dynamic_provider.py
llm_council/metadata/intersection.py
llm_council/metadata/litellm_adapter.py
llm_council/metadata/offline.py
llm_council/metadata/openrouter_client.py
llm_council/metadata/protocol.py
llm_council/metadata/registry.py
llm_council/metadata/scoring.py
llm_council/metadata/selection.py
llm_council/metadata/startup.py
llm_council/metadata/static_registry.py
llm_council/metadata/types.py
llm_council/metadata/worker.py
llm_council/models/registry.yaml
llm_council/observability/__init__.py
llm_council/observability/metrics_adapter.py
llm_council/performance/__init__.py
llm_council/performance/integration.py
llm_council_core-0.24.21.dist-info/METADATA
llm_council_core-0.24.21.dist-info/WHEEL
llm_council_core-0.24.21.dist-info/entry_points.txt
llm_council_core-0.24.21.dist-info/licenses/LICENSE
llm_council_core-0.24.21.dist-info/RECORD
