Metadata-Version: 2.4
Name: llm-council-core
Version: 0.24.21
Summary: Multi-LLM council system with peer review and synthesis
Project-URL: Homepage, https://github.com/amiable-dev/llm-council
Project-URL: Repository, https://github.com/amiable-dev/llm-council
Project-URL: Issues, https://github.com/amiable-dev/llm-council/issues
Project-URL: Documentation, https://llm-council.dev
Author: Amiable
Maintainer-email: contact@amiable.dev
License: MIT
License-File: LICENSE
Keywords: ai,claude,council,gemini,gpt,llm,multi-model,openrouter
Classifier: Development Status :: 4 - Beta
Classifier: Intended Audience :: Developers
Classifier: License :: OSI Approved :: MIT License
Classifier: Programming Language :: Python :: 3
Classifier: Programming Language :: Python :: 3.10
Classifier: Programming Language :: Python :: 3.11
Classifier: Programming Language :: Python :: 3.12
Classifier: Programming Language :: Python :: 3.13
Classifier: Topic :: Scientific/Engineering :: Artificial Intelligence
Classifier: Topic :: Software Development :: Libraries :: Python Modules
Requires-Python: >=3.10
Requires-Dist: httpx>=0.27.0
Requires-Dist: pydantic>=2.0.0
Requires-Dist: python-dotenv>=1.0.0
Requires-Dist: pyyaml>=6.0.3
Provides-Extra: all
Requires-Dist: fastapi>=0.100.0; extra == 'all'
Requires-Dist: mcp>=1.22.0; extra == 'all'
Requires-Dist: uvicorn>=0.20.0; extra == 'all'
Provides-Extra: dev
Requires-Dist: mypy>=1.0.0; extra == 'dev'
Requires-Dist: pytest-asyncio>=0.21.0; extra == 'dev'
Requires-Dist: pytest-cov>=4.0.0; extra == 'dev'
Requires-Dist: pytest-recording>=0.13.0; extra == 'dev'
Requires-Dist: pytest>=7.0; extra == 'dev'
Requires-Dist: ruff>=0.1.0; extra == 'dev'
Requires-Dist: tomli>=2.0.0; (python_version < '3.11') and extra == 'dev'
Requires-Dist: vcrpy>=6.0.0; extra == 'dev'
Provides-Extra: docs
Requires-Dist: mkdocs-material>=9.5.0; extra == 'docs'
Requires-Dist: mkdocs>=1.5.0; extra == 'docs'
Provides-Extra: http
Requires-Dist: fastapi>=0.100.0; extra == 'http'
Requires-Dist: uvicorn>=0.20.0; extra == 'http'
Provides-Extra: mcp
Requires-Dist: mcp>=1.22.0; extra == 'mcp'
Provides-Extra: ollama
Requires-Dist: litellm>=1.50.0; extra == 'ollama'
Provides-Extra: secure
Requires-Dist: keyring>=23.0.0; extra == 'secure'
